{
  "protocol_name": "a_train_seed_final_probe_diagnostic_v1",
  "created_at": "2026-05-24T14:26:29+08:00",
  "diagnostic_scope": "A_only_train_seed_probe",
  "purpose": "Diagnose train-seed vs held-out final-seed differences for A_full_method_main.",
  "not_replacement_for": "C:\\Users\\Dk\\Desktop\\SCI\\DRL_PF\\experiment_records\\final_probe",
  "method_id": "A",
  "episodes": 100,
  "seed_base": 20259323,
  "episode_seed_rule": "seed_base + zero_based_episode_index",
  "policy": "greedy",
  "device": "cuda",
  "checkpoint_path": "C:\\Users\\Dk\\Desktop\\SCI\\DRL_PF\\checkpoint_store\\full_method_main\\A_full_method.pt",
  "config_snapshot_path": "C:\\Users\\Dk\\Desktop\\SCI\\DRL_PF\\experiment_records\\full_method_main\\logs\\config_snapshot.json",
  "method_loading": {
    "model_factory": "ExplorationQNetwork",
    "state_adapter_factory": "StateTensorAdapter"
  },
  "env_params": {
    "rows": 40,
    "cols": 60,
    "obs_size": 6,
    "scan_radius": 10,
    "obstacle_ratio": 0.2,
    "max_episode_steps": 600,
    "coverage_stop_threshold": 0.95,
    "trajectory_history_steps": 10
  },
  "checkpoint_copy_policy": "checkpoint is referenced in place and is not copied into experiment_records",
  "official_final_probe_reference": "C:\\Users\\Dk\\Desktop\\SCI\\DRL_PF\\experiment_records\\final_probe"
}
